pytest_timestamps/__init__.py
pytest_timestamps/plugin.py
pytest_timestamps/reporter.py
pytest_timestamps/timestamp.py
pytest_timestamps-0.2.1.dist-info/METADATA
pytest_timestamps-0.2.1.dist-info/WHEEL
pytest_timestamps-0.2.1.dist-info/entry_points.txt
pytest_timestamps-0.2.1.dist-info/RECORD
