Metadata-Version: 2.1
Name: pytest-timestamps
Version: 0.2.1
Summary: A simple plugin to view timestamps for each test
Author: TJ
Author-email: tbruno25@gmail.com
Requires-Python: >=3.8,<4.0
Classifier: Programming Language :: Python :: 3
Classifier: Programming Language :: Python :: 3.8
Classifier: Programming Language :: Python :: 3.9
Classifier: Programming Language :: Python :: 3.10
Classifier: Programming Language :: Python :: 3.11
Requires-Dist: pytest (>=7.3,<8.0)
